fifo/syn_fifo.v
module syn_fifo(
    input clk,            // Clock input
    input rst,            // Reset input
    input write_en,       // Write enable input
    input [7:0] data_in,  // Data input
    output full,      // Full flag output
    output empty,
    input read_en,        // Read enable input
    output reg [7:0] data_out // Data output
);

parameter DEPTH = 15;  // Depth of the FIFO

reg [7:0] memory [0:DEPTH-1];  // Internal memory to store data
reg [3:0] write_ptr = 4'b0000; // Write pointer
reg [3:0] read_ptr = 4'b0000;  // Read pointer



// Write operation
always @(posedge clk) begin
    if (rst) begin
        write_ptr <= 4'b0000;  // Reset write pointer
    end else if (write_en && !full) begin
        memory[write_ptr] <= data_in;  // Write data to memory
        write_ptr <= write_ptr + 1'b1;     // Increment write pointer
    end
end

// Read operation
always @(posedge clk) begin
    if (rst) begin
        read_ptr <= 4'b0000;  // Reset read pointer
    end else if (read_en && !empty) begin
        data_out <= memory[read_ptr];  // Read data from memory
        read_ptr <= read_ptr + 1'b1;       // Increment read pointer
    end
end
assign full = ((write_ptr + 1'b1) == read_ptr);
assign empty = (write_ptr == read_ptr);

endmodule

fifo/syn_fifo_tb.v
`timescale 1ns / 1ps

module testbench_synchronous_fifo;

// Inputs
reg clk;
reg rst;
reg write_en;
reg [7:0] data_in;
reg read_en;

// Outputs
wire full, empty;
wire [7:0] data_out;

// Instantiate the synchronous FIFO module
syn_fifo dut(
    .clk(clk),
    .rst(rst),
    .write_en(write_en),
    .data_in(data_in),
    .full(full),
    .empty(empty),
    .read_en(read_en),
    .data_out(data_out)
);

// Clock generation
initial begin
    clk = 0;
    forever #5 clk = ~clk;
end

// Stimulus
initial begin
    $dumpfile("wf.vcd");
    $dumpvars();
    // Reset sequence
    rst = 1;
    write_en = 0;
    read_en = 0;
    data_in = 8'h00;
    #10;
    rst = 0;
    #10;

    // Write data to FIFO
    write_en = 1;
    repeat(17) begin
        data_in = $random;
        #10;
    end
    write_en = 0;

    // Read data from FIFO
    read_en = 1;
    repeat(17) begin
        #15;
    end
    read_en = 0;

    // Finish simulation
    #10;
    $finish;
end

endmodule

fifo/wf.vcd
$date
	Tue Apr 23 10:02:49 2024
$end
$version
	Icarus Verilog
$end
$timescale
	1ps
$end
$scope module testbench_synchronous_fifo $end
$var wire 1 ! full $end
$var wire 1 " empty $end
$var wire 8 # data_out [7:0] $end
$var reg 1 $ clk $end
$var reg 8 % data_in [7:0] $end
$var reg 1 & read_en $end
$var reg 1 ' rst $end
$var reg 1 ( write_en $end
$scope module dut $end
$var wire 1 $ clk $end
$var wire 8 ) data_in [7:0] $end
$var wire 1 & read_en $end
$var wire 1 ' rst $end
$var wire 1 ( write_en $end
$var wire 1 ! full $end
$var wire 1 " empty $end
$var reg 8 * data_out [7:0] $end
$var reg 4 + read_ptr [3:0] $end
$var reg 4 , write_ptr [3:0] $end
$upscope $end
$upscope $end
$enddefinitions $end
#0
$dumpvars
b0 ,
b0 +
bx *
b0 )
0(
1'
0&
b0 %
0$
bx #
1"
0!
$end
#5000
1$
#10000
0$
0'
#15000
1$
#20000
0$
b100100 %
b100100 )
1(
#25000
0"
b1 ,
1$
#30000
0$
b10000001 %
b10000001 )
#35000
b10 ,
1$
#40000
0$
b1001 %
b1001 )
#45000
b11 ,
1$
#50000
0$
b1100011 %
b1100011 )
#55000
b100 ,
1$
#60000
0$
b1101 %
b1101 )
#65000
b101 ,
1$
#70000
0$
b10001101 %
b10001101 )
#75000
b110 ,
1$
#80000
0$
b1100101 %
b1100101 )
#85000
b111 ,
1$
#90000
0$
b10010 %
b10010 )
#95000
b1000 ,
1$
#100000
0$
b1 %
b1 )
#105000
b1001 ,
1$
#110000
0$
b1101 %
b1101 )
#115000
b1010 ,
1$
#120000
0$
b1110110 %
b1110110 )
#125000
b1011 ,
1$
#130000
0$
b111101 %
b111101 )
#135000
b1100 ,
1$
#140000
0$
b11101101 %
b11101101 )
#145000
b1101 ,
1$
#150000
0$
b10001100 %
b10001100 )
#155000
b1110 ,
1$
#160000
0$
b11111001 %
b11111001 )
#165000
1!
b1111 ,
1$
#170000
0$
b11000110 %
b11000110 )
#175000
1$
#180000
0$
b11000101 %
b11000101 )
#185000
1$
#190000
0$
1&
0(
#195000
0!
b1 +
b100100 #
b100100 *
1$
#200000
0$
#205000
b10 +
b10000001 #
b10000001 *
1$
#210000
0$
#215000
b11 +
b1001 #
b1001 *
1$
#220000
0$
#225000
b100 +
b1100011 #
b1100011 *
1$
#230000
0$
#235000
b101 +
b1101 #
b1101 *
1$
#240000
0$
#245000
b110 +
b10001101 #
b10001101 *
1$
#250000
0$
#255000
b111 +
b1100101 #
b1100101 *
1$
#260000
0$
#265000
b1000 +
b10010 #
b10010 *
1$
#270000
0$
#275000
b1001 +
b1 #
b1 *
1$
#280000
0$
#285000
b1010 +
b1101 #
b1101 *
1$
#290000
0$
#295000
b1011 +
b1110110 #
b1110110 *
1$
#300000
0$
#305000
b1100 +
b111101 #
b111101 *
1$
#310000
0$
#315000
b1101 +
b11101101 #
b11101101 *
1$
#320000
0$
#325000
b1110 +
b10001100 #
b10001100 *
1$
#330000
0$
#335000
1"
b1111 +
b11111001 #
b11111001 *
1$
#340000
0$
#345000
1$
#350000
0$
#355000
1$
#360000
0$
#365000
1$
#370000
0$
#375000
1$
#380000
0$
#385000
1$
#390000
0$
#395000
1$
#400000
0$
#405000
1$
#410000
0$
#415000
1$
#420000
0$
#425000
1$
#430000
0$
#435000
1$
#440000
0$
#445000
1$
0&
