counter/counter_4bit.v
module counter_4bit(
    input clk,          // Clock input
    input reset,        // Reset input
    output reg [3:0] count  // 4-bit count output
);

always @(posedge clk or posedge reset) begin
    if (reset)
        count <= 4'b0000;  // Reset the count to 0
    else
        count <= count + 1;  // Increment count on each clock cycle
end

endmodule

counter/counter_4bit_tb.v
`timescale 1ns / 1ps  // Specify simulation time scale

module testbench_counter_4bit;

// Inputs
reg clk;    // Clock input
reg reset;  // Reset input

// Outputs
wire [3:0] count;  // 4-bit count output

// Instantiate the 4-bit counter module
counter_4bit dut(
    .clk(clk),
    .reset(reset),
    .count(count)
);

// Clock generation
always begin
    clk = 0;
    #5;  // Half clock period
    clk = 1;
    #5;  // Half clock period
end

// Stimulus
initial begin
    $dumpfile("counter_4bit.vcd");  // Dump waveform to a VCD file
    $dumpvars(0, testbench_counter_4bit);  // Dump all variables

    reset = 1;  // Assert reset initially
    #10;       // Wait for a few cycles
    reset = 0;  // De-assert reset

    // Wait for 20 clock cycles to observe the count
    #100;

    $finish;  // End simulation
end

endmodule

counter/counter_4bit.vcd
$date
	Mon Apr 22 22:00:16 2024
$end
$version
	Icarus Verilog
$end
$timescale
	1ps
$end
$scope module testbench_counter_4bit $end
$var wire 4 ! count [3:0] $end
$var reg 1 " clk $end
$var reg 1 # reset $end
$scope module dut $end
$var wire 1 " clk $end
$var wire 1 # reset $end
$var reg 4 $ count [3:0] $end
$upscope $end
$upscope $end
$enddefinitions $end
#0
$dumpvars
b0 $
1#
0"
b0 !
$end
#5000
1"
#10000
0"
0#
#15000
b1 !
b1 $
1"
#20000
0"
#25000
b10 !
b10 $
1"
#30000
0"
#35000
b11 !
b11 $
1"
#40000
0"
#45000
b100 !
b100 $
1"
#50000
0"
#55000
b101 !
b101 $
1"
#60000
0"
#65000
b110 !
b110 $
1"
#70000
0"
#75000
b111 !
b111 $
1"
#80000
0"
#85000
b1000 !
b1000 $
1"
#90000
0"
#95000
b1001 !
b1001 $
1"
#100000
0"
#105000
b1010 !
b1010 $
1"
