FSM/fsm_moore.v
module moore_fsm (
    input clk,          // Clock input
    input reset,        // Reset input
    input in,           // Input signal
    output reg out      // Output signal
);

// Define states
parameter STATE_A = 2'b00;
parameter STATE_B = 2'b01;

// Define state register
reg [1:0] state;

// Moore output logic
always @(state) begin
    case (state)
        STATE_A: out = 1;  // Output is 1 in state A
        STATE_B: out = 0;  // Output is 0 in state B
        default: out = 1;  // Default output
    endcase
end

// Next state logic
always @(posedge clk or posedge reset) begin
    if (reset) begin
        state <= STATE_A;  // Reset to initial state
    end else begin
        case (state)
            STATE_A: state <= in ? STATE_B : STATE_A;  // Transition to state B on input 1
            STATE_B: state <= in ? STATE_B : STATE_A;  // Transition to state A on input 0
            default: state <= STATE_A;  // Default transition
        endcase
    end
end

endmodule

FSM/fsm_moore_tb.v
`timescale 1ns / 1ps

module testbench_moore_fsm;

// Inputs
reg clk;
reg reset;
reg in;

// Outputs
wire out;

// Instantiate the Moore FSM module
moore_fsm dut (
    .clk(clk),
    .reset(reset),
    .in(in),
    .out(out)
);

// Clock generation
initial begin
    clk = 0;
    forever #5 clk = ~clk;
end

// Stimulus
initial begin
    $dumpfile("wf.vcd");
    $dumpvars();
    reset = 1;
    in = 0;
    #10;
    reset = 0;
    #20;
    in = 1; // transition from STATE_A to STATE_B
    #10;
    in = 0; // transition from STATE_B to STATE_A
    #20;
    in = 1; // transition from STATE_A to STATE_B
    #10;
    $finish;
end

endmodule

FSM/wf.vcd
$date
	Mon Apr 22 22:09:45 2024
$end
$version
	Icarus Verilog
$end
$timescale
	1ps
$end
$scope module testbench_moore_fsm $end
$var wire 1 ! out $end
$var reg 1 " clk $end
$var reg 1 # in $end
$var reg 1 $ reset $end
$scope module dut $end
$var wire 1 " clk $end
$var wire 1 # in $end
$var wire 1 $ reset $end
$var reg 1 ! out $end
$var reg 2 % state [1:0] $end
$upscope $end
$upscope $end
$enddefinitions $end
#0
$dumpvars
b0 %
1$
0#
0"
1!
$end
#5000
1"
#10000
0"
0$
#15000
1"
#20000
0"
#25000
1"
#30000
0"
1#
#35000
0!
b1 %
1"
#40000
0"
0#
#45000
1!
b0 %
1"
#50000
0"
#55000
1"
#60000
0"
1#
#65000
0!
b1 %
1"
