full_adder/full_adder.v
module full_adder(
    input A, 
    input B, 
    input Cin,
    output S, 
    output Cout
);

assign S = A ^ B ^ Cin;  // XOR operation for sum
assign Cout = (A & B) | (B & Cin) | (A & Cin);  // OR operation for carry out

endmodule

full_adder/full_adder_tb.v
`timescale 1ns / 1ps  // Specify simulation time scale

module testbench_full_adder;

// Inputs
reg A, B, Cin;

// Outputs
wire S, Cout;

// Instantiate the full adder module
full_adder dut(
    .A(A),
    .B(B),
    .Cin(Cin),
    .S(S),
    .Cout(Cout)
);

// Stimulus
initial begin
    $dumpfile("full_adder.vcd");  // Dump waveform to a VCD file
    $dumpvars(0, testbench_full_adder);  // Dump all variables

    // Test case 1: A=0, B=0, Cin=0
    A = 0; B = 0; Cin = 0;
    #10;  // Wait for 10 time units
    // Expected output: S=0, Cout=0

    // Test case 2: A=0, B=0, Cin=1
    A = 0; B = 0; Cin = 1;
    #10;  // Wait for 10 time units
    // Expected output: S=1, Cout=0

    // Test case 3: A=0, B=1, Cin=0
    A = 0; B = 1; Cin = 0;
    #10;  // Wait for 10 time units
    // Expected output: S=1, Cout=0

    // Test case 4: A=0, B=1, Cin=1
    A = 0; B = 1; Cin = 1;
    #10;  // Wait for 10 time units
    // Expected output: S=0, Cout=1

    // Test case 5: A=1, B=0, Cin=0
    A = 1; B = 0; Cin = 0;
    #10;  // Wait for 10 time units
    // Expected output: S=1, Cout=0

    // Test case 6: A=1, B=0, Cin=1
    A = 1; B = 0; Cin = 1;
    #10;  // Wait for 10 time units
    // Expected output: S=0, Cout=1

    // Test case 7: A=1, B=1, Cin=0
    A = 1; B = 1; Cin = 0;
    #10;  // Wait for 10 time units
    // Expected output: S=0, Cout=1

    // Test case 8: A=1, B=1, Cin=1
    A = 1; B = 1; Cin = 1;
    #10;  // Wait for 10 time units
    // Expected output: S=1, Cout=1

    $finish;  // End simulation
end

endmodule

full_adder/full_adder.vcd
$date
	Mon Apr 22 20:20:28 2024
$end
$version
	Icarus Verilog
$end
$timescale
	1ps
$end
$scope module testbench_full_adder $end
$var wire 1 ! S $end
$var wire 1 " Cout $end
$var reg 1 # A $end
$var reg 1 $ B $end
$var reg 1 % Cin $end
$scope module dut $end
$var wire 1 # A $end
$var wire 1 $ B $end
$var wire 1 % Cin $end
$var wire 1 " Cout $end
$var wire 1 ! S $end
$upscope $end
$upscope $end
$enddefinitions $end
#0
$dumpvars
0%
0$
0#
0"
0!
$end
#10000
1!
1%
#20000
0%
1$
#30000
1"
0!
1%
#40000
0"
1!
0%
0$
1#
#50000
1"
0!
1%
#60000
0%
1$
#70000
1!
1%
